{
    "AX": {
        "error": 0.0,
        "fit": "default",
        "references": [],
        "value": 1.0
    },
    "CDD": {
        "error": 0.00222471384227614,
        "fit": "Average",
        "reference_data": {
            "es": [
                0.0018801423190854857,
                0.001882840653394529,
                0.0018959769349398616,
                0.0018091433736287595,
                0.001890251390960305
            ],
            "vs": [
                1.0708836372053887,
                1.0706638919116773,
                1.0683017341616494,
                1.0723575458834604,
                1.074318533146542
            ],
            "xs": [
                1727106119.0,
                1727108981.0,
                1727119463.0,
                1727129985.0,
                1727140473.0
            ]
        },
        "reference_detector": "H1",
        "references": [
            {
                "exclude": "ok",
                "record_id": "a-01-A-9065",
                "uuid": "1d99db95-c8a8-4c51-88ee-51492f458bf9"
            },
            {
                "exclude": "ok",
                "record_id": "a-01-A-9066",
                "uuid": "7423e1c3-df79-49cf-b62e-c8ee949842c4"
            },
            {
                "exclude": "ok",
                "record_id": "a-01-A-9067",
                "uuid": "b1290385-6ded-4d9b-a5f1-c50308d35176"
            },
            {
                "exclude": "ok",
                "record_id": "a-01-A-9068",
                "uuid": "6eca8bf3-65bd-4c66-a387-3222557cac0b"
            },
            {
                "exclude": "ok",
                "record_id": "a-01-A-9069",
                "uuid": "bf326cce-4513-44da-b4ab-c232d434686e"
            }
        ],
        "reviewed": true,
        "standard_ratio": 295.5,
        "value": 1.0713050684617436
    },
    "H1": {
        "error": 0.0,
        "fit": "default",
        "references": [],
        "value": 1.0
    },
    "L1": {
        "error": 0.0,
        "fit": "default",
        "references": [],
        "value": 1.0
    },
    "L2": {
        "error": 0.0,
        "fit": "default",
        "references": [],
        "value": 1.0
    }
}