{
    "Ar36": {
        "error": 0.00032097043066504536,
        "error_type": "",
        "fit": "previous",
        "references": [
            {
                "exclude": false,
                "record_id": "ba-01-A-29334"
            }
        ],
        "value": 0.020967103734412785
    },
    "Ar37": {
        "error": 0.009319574555851808,
        "error_type": "",
        "fit": "previous",
        "references": [
            {
                "exclude": false,
                "record_id": "ba-01-A-29334"
            }
        ],
        "value": 0.03580941204156176
    },
    "Ar38": {
        "error": 0.0108462531677706,
        "error_type": "",
        "fit": "previous",
        "references": [
            {
                "exclude": false,
                "record_id": "ba-01-A-29334"
            }
        ],
        "value": -0.0037962059327973988
    },
    "Ar39": {
        "error": 0.008842180828664345,
        "error_type": "",
        "fit": "previous",
        "references": [
            {
                "exclude": false,
                "record_id": "ba-01-A-29334"
            }
        ],
        "value": 0.046774622552169916
    },
    "Ar40": {
        "error": 0.02326340750304087,
        "error_type": "",
        "fit": "previous",
        "references": [
            {
                "exclude": false,
                "record_id": "ba-01-A-29334"
            }
        ],
        "value": 5.661616756938714
    }
}