{
    "AX": {
        "error": 0.0,
        "fit": "default",
        "references": [],
        "value": 1.0
    },
    "CDD": {
        "error": 0.0010795319651346568,
        "fit": "Average",
        "reference_data": {
            "es": [
                0.0018807333635447424,
                0.0016669174128999518,
                0.0018391704077110266,
                0.0019454581490941454
            ],
            "vs": [
                1.0598070782410556,
                1.0682961613717818,
                1.0591175406141897,
                1.0612341929415972
            ],
            "xs": [
                1725002346.0,
                1725012638.0,
                1725022947.0,
                1725033258.0
            ]
        },
        "reference_detector": "H1",
        "references": [
            {
                "exclude": "ok",
                "record_id": "a-01-A-8924",
                "uuid": "4c98c0be-ba86-4b13-9e39-cf56764369de"
            },
            {
                "exclude": "omit",
                "record_id": "a-01-A-8925",
                "uuid": "a0400756-16b7-4e1f-9575-5d88334a3d51"
            },
            {
                "exclude": "ok",
                "record_id": "a-01-A-8926",
                "uuid": "b1fa7372-988f-49d0-aaa2-be03ae3ad2d0"
            },
            {
                "exclude": "ok",
                "record_id": "a-01-A-8927",
                "uuid": "358e5a36-17eb-46ee-b64f-dac1626c1ec7"
            }
        ],
        "reviewed": true,
        "standard_ratio": 295.5,
        "value": 1.060052937265614
    },
    "H1": {
        "error": 0.0,
        "fit": "default",
        "references": [],
        "value": 1.0
    },
    "L1": {
        "error": 0.0,
        "fit": "default",
        "references": [],
        "value": 1.0
    },
    "L2": {
        "error": 0.0,
        "fit": "default",
        "references": [],
        "value": 1.0
    }
}